hit/__init__.py
hit/exceptions.py
hit/ele/__init__.py
hit/ids/__init__.py
hit/ids/login.py
hit/ids/utils.py
hit/timetable/__init__.py
hitutil-0.5.0.dist-info/LICENSE
hitutil-0.5.0.dist-info/METADATA
hitutil-0.5.0.dist-info/WHEEL
hitutil-0.5.0.dist-info/top_level.txt
hitutil-0.5.0.dist-info/RECORD
