Metadata-Version: 2.1
Name: hitutil
Version: 0.5.0
Summary: hit.edu.cn utils
Home-page: https://github.com/billchenchina/hitutil
Author: Billchenchina
Author-email: billchenchina2001@gmail.com
License: UNKNOWN
Project-URL: Bug Reports, https://github.com/billchenchina/hitutil/issues
Project-URL: Source, https://github.com/billchenchina/hitutil/
Keywords: Harbin Institute of Technology,HIT,requests
Platform: UNKNOWN
Classifier: Development Status :: 2 - Pre-Alpha
Classifier: Intended Audience :: Developers
Classifier: License :: OSI Approved :: GNU Affero General Public License v3 or later (AGPLv3+)
Classifier: Natural Language :: Chinese (Simplified)
Classifier: Natural Language :: English
Classifier: Operating System :: MacOS
Classifier: Operating System :: Microsoft :: Windows
Classifier: Operating System :: POSIX :: Linux
Classifier: Programming Language :: Python :: 3
Classifier: Programming Language :: Python :: 3.7
Classifier: Programming Language :: Python :: 3.8
Classifier: Programming Language :: Python :: 3.9
Classifier: Programming Language :: Python :: 3 :: Only
Classifier: Topic :: Utilities
Requires-Python: >=3.5, <4
Requires-Dist: beautifulsoup4
Requires-Dist: pandas
Requires-Dist: pycryptodome
Requires-Dist: requests
